mcp_scholarly/__init__.py
mcp_scholarly/arxiv_search.py
mcp_scholarly/google_scholar.py
mcp_scholarly/server.py
mseep_mcp_scholarly-0.1.4.dist-info/licenses/LICENSE
mseep_mcp_scholarly-0.1.4.dist-info/METADATA
mseep_mcp_scholarly-0.1.4.dist-info/WHEEL
mseep_mcp_scholarly-0.1.4.dist-info/entry_points.txt
mseep_mcp_scholarly-0.1.4.dist-info/top_level.txt
mseep_mcp_scholarly-0.1.4.dist-info/RECORD
