Metadata-Version: 2.4
Name: mseep-mcp-scholarly
Version: 0.1.4
Summary: A MCP server to search for accurate academic articles.
Author-email: mseep <support@skydeck.ai>
Requires-Python: >=3.11
License-File: LICENSE
Requires-Dist: arxiv>=2.1.3
Requires-Dist: free-proxy>=1.1.3
Requires-Dist: mcp>=1.1.2
Requires-Dist: scholarly>=1.7.11
Dynamic: license-file
